{
  "parryTicks": 0,
  "meleeDamageTakenAfterBlock": 0.80,
  "projectileDamageTakenAfterBlock": 0.95,
  "cooldownAfterParryAction": -2.5,
  "cooldownAfterInterruptingBlockAction": -2.8,
  "maxUseTime": 7200,
  "shouldStopUsingItemAfterBlockOrParry": true,
  "knockbackAfterParryAction": 5.0,
  "parryEffects": [
    {
      "statusEffect": "minecraft:slowness",
      "duration": 100,
      "amplifier": 1,
      "chance": 1.0,
      "enchantmentMultiplier": 0.3
    },
    {
      "statusEffect": "frycparry:disarmed",
      "duration": 20,
      "amplifier": 1,
      "chance": 1.0,
      "enchantmentMultiplier": 0.12
    }
  ]
}