{
  "required": true,
  "minVersion": "0.8",
  "package": "net.fryc.frycparry.mixin",
  "compatibilityLevel": "JAVA_17",
  "mixins": [
    "items/ItemStackMixin",
    "items/ShieldMixin",
    "items/SwordMixin",
    "items/AxeMixin",
    "items/PickaxeMixin",
    "items/ShovelMixin",
    "items/HoeMixin",
    "items/ToolItemMixin",
    "LivingEntityMixin",
    "PlayerEntityMixin",
    "EnchantmentHelperMixin",
    "ServerPlayerInteractionManagerMixin",
    "ServerPlayNetworkHandlerMixin",
    "ServerWorldMixin"
  ],
  "client": [
    "client/MinecraftClientMixin",
    "client/ClientPlayerInteractionManagerMixin",
    "client/PlayerEntityRendererMixin",
    "client/HeldItemRendererMixin",
    "client/TransformationMixin",
    "client/ItemRendererMixin"
  ],
  "injectors": {
    "defaultRequire": 1
  }
}
